{
  "annotations": { "list": [] },
  "editable": true,
  "fiscalYearStartMonth": 0,
  "graphTooltip": 1,
  "id": null,
  "links": [],
  "templating": {
    "list": [
      {
        "name": "datasource",
        "label": "Data source",
        "type": "datasource",
        "query": "prometheus",
        "current": {},
        "hide": 0,
        "includeAll": false,
        "multi": false,
        "refresh": 1,
        "regex": ""
      }
    ]
  },
  "panels": [
    {
      "datasource": { "type": "prometheus", "uid": "${datasource}" },
      "fieldConfig": {
        "defaults": {
          "unit": "reqps",
          "custom": {
            "drawStyle": "line",
            "fillOpacity": 10,
            "lineWidth": 2,
            "showPoints": "never"
          }
        },
        "overrides": []
      },
      "gridPos": { "h": 8, "w": 12, "x": 0, "y": 0 },
      "id": 1,
      "options": {
        "legend": { "displayMode": "list", "placement": "bottom" },
        "tooltip": { "mode": "single" }
      },
      "title": "Request Rate",
      "type": "timeseries",
      "targets": [
        {
          "datasource": { "type": "prometheus", "uid": "${datasource}" },
          "expr": "sum(rate(http_server_duration_milliseconds_count[1m]))",
          "legendFormat": "requests/sec",
          "refId": "A"
        }
      ]
    },
    {
      "datasource": { "type": "prometheus", "uid": "${datasource}" },
      "fieldConfig": {
        "defaults": {
          "unit": "ms",
          "thresholds": {
            "mode": "absolute",
            "steps": [
              { "color": "green", "value": null },
              { "color": "yellow", "value": 200 },
              { "color": "red", "value": 1000 }
            ]
          },
          "custom": {
            "drawStyle": "line",
            "fillOpacity": 10,
            "lineWidth": 2,
            "showPoints": "never"
          }
        },
        "overrides": []
      },
      "gridPos": { "h": 8, "w": 12, "x": 12, "y": 0 },
      "id": 2,
      "options": {
        "legend": { "displayMode": "list", "placement": "bottom" },
        "tooltip": { "mode": "single" }
      },
      "title": "Request Latency (p50 / p95 / p99)",
      "type": "timeseries",
      "targets": [
        {
          "datasource": { "type": "prometheus", "uid": "${datasource}" },
          "expr": "histogram_quantile(0.50, sum(rate(http_server_duration_milliseconds_bucket[5m])) by (le))",
          "legendFormat": "p50",
          "refId": "A"
        },
        {
          "datasource": { "type": "prometheus", "uid": "${datasource}" },
          "expr": "histogram_quantile(0.95, sum(rate(http_server_duration_milliseconds_bucket[5m])) by (le))",
          "legendFormat": "p95",
          "refId": "B"
        },
        {
          "datasource": { "type": "prometheus", "uid": "${datasource}" },
          "expr": "histogram_quantile(0.99, sum(rate(http_server_duration_milliseconds_bucket[5m])) by (le))",
          "legendFormat": "p99",
          "refId": "C"
        }
      ]
    },
    {
      "datasource": { "type": "prometheus", "uid": "${datasource}" },
      "fieldConfig": {
        "defaults": {
          "unit": "percentunit",
          "min": 0,
          "max": 1,
          "thresholds": {
            "mode": "absolute",
            "steps": [
              { "color": "green", "value": null },
              { "color": "red", "value": 0.05 }
            ]
          },
          "custom": {
            "drawStyle": "line",
            "fillOpacity": 10,
            "lineWidth": 2,
            "showPoints": "never"
          }
        },
        "overrides": []
      },
      "gridPos": { "h": 8, "w": 12, "x": 0, "y": 8 },
      "id": 3,
      "options": {
        "legend": { "displayMode": "list", "placement": "bottom" },
        "tooltip": { "mode": "single" }
      },
      "title": "Error Rate (5xx)",
      "type": "timeseries",
      "targets": [
        {
          "datasource": { "type": "prometheus", "uid": "${datasource}" },
          "expr": "sum(rate(http_server_duration_milliseconds_count{http_status_code=~\"5..\"}[5m])) / sum(rate(http_server_duration_milliseconds_count[5m]))",
          "legendFormat": "5xx rate",
          "refId": "A"
        }
      ]
    },
    {
      "datasource": { "type": "prometheus", "uid": "${datasource}" },
      "fieldConfig": { "defaults": {} },
      "gridPos": { "h": 8, "w": 12, "x": 12, "y": 8 },
      "id": 4,
      "options": {
        "showHeader": true,
        "sortBy": [{ "displayName": "Value", "desc": true }]
      },
      "title": "Requests by Endpoint",
      "type": "table",
      "targets": [
        {
          "datasource": { "type": "prometheus", "uid": "${datasource}" },
          "expr": "sum by (http_target) (increase(http_server_duration_milliseconds_count[1h]))",
          "legendFormat": "{{ http_target }}",
          "refId": "A",
          "format": "table",
          "instant": true
        }
      ]
    }
  ],
  "schemaVersion": 39,
  "tags": ["reckon", "api"],
  "time": { "from": "now-1h", "to": "now" },
  "title": "API Health",
  "uid": "reckon-api-health"
}
